{
  "repo": "geotab",
  "blogURL": "https://www.geotab.com/blog/",
  "blogRSS": null,
  "rssConfirmed": false,
  "rssProbed": [
    "https://www.geotab.com/blog/feed/",
    "https://www.geotab.com/blog/rss/",
    "https://www.geotab.com/blog/feed.xml",
    "https://www.geotab.com/blog/atom.xml",
    "https://www.geotab.com/blog/index.xml",
    "https://www.geotab.com/blog/rss.xml",
    "https://www.geotab.com/feed/"
  ],
  "note": "No RSS or Atom feed discovered; all standard feed paths return 404 and the blog HTML head exposes no feed link. Posts pulled via HTML scraping of geotab.com/blog/.",
  "lastChecked": "2026-06-21",
  "feeds": [
    {
      "source": "https://www.geotab.com/blog/",
      "feed_url": "",
      "saved": 1,
      "method": "agent-scrape"
    }
  ],
  "fetched": "2026-06-27T12:43:37Z",
  "agent_pulled": "2026-06-27",
  "post_count": 6
}
